setup.py
trello_cms/__init__.py
trello_cms/__main__.py
trello_cms/core.py
trello_cms/utils.py
trello_cms.egg-info/PKG-INFO
trello_cms.egg-info/SOURCES.txt
trello_cms.egg-info/dependency_links.txt
trello_cms.egg-info/requires.txt
trello_cms.egg-info/top_level.txt