Metadata-Version: 1.1
Name: trello-cms
Version: 0.1.1
Summary: Build websites with Trello data
Home-page: https://github.com/jacoduplessis/trello_cms
Author: Jaco du Plessis
Author-email: jaco@jacoduplessis.co.za
License: UNKNOWN
Keywords: trello cms ssg
Platform: UNKNOWN
Classifier: Programming Language :: Python :: 3
